cve_prioritizer/__init__.py
cve_prioritizer/__main__.py
cve_prioritizer/cve_prioritizer.py
cve_prioritizer/test_vulnrichment_cve_prioritizer.py
scripts/__init__.py
scripts/constants.py
scripts/helpers.py
scripts/test_cpe_helpers.py
scripts/test_vulnrichment_helpers.py
scripts/test_vulnrishment_helpers.py
cve_prioritizer-1.8.3.dist-info/LICENSE
cve_prioritizer-1.8.3.dist-info/METADATA
cve_prioritizer-1.8.3.dist-info/WHEEL
cve_prioritizer-1.8.3.dist-info/entry_points.txt
cve_prioritizer-1.8.3.dist-info/top_level.txt
cve_prioritizer-1.8.3.dist-info/RECORD
