Metadata-Version: 2.2
Name: cve-prioritizer
Version: 1.8.3
Summary: Streamline vulnerability patching with CVSS, EPSS, and CISA's Known Exploited Vulnerabilities Prioritize actions based on real-time threat information, gain a competitive advantage, and stay informed about the latest trends.
Home-page: https://github.com/TURROKS/CVE_Prioritizer
Author: Mario Rojas
Author-email: Mario Rojas <prioritizer@proton.me>
Maintainer-email: Mario Rojas <prioritizer@proton.me>
License: BSD 3-Clause
Keywords: CVE,CVSS,EPSS,CISA,Prioritize,Vulnerability
Requires-Python: >=3.6
License-File: LICENSE
Requires-Dist: click>=8.0.3
Requires-Dist: pandas>=1.5.3
Requires-Dist: python-dotenv>=0.19.2
Requires-Dist: requests>=2.32.3
Requires-Dist: termcolor>=2.2.0
Dynamic: author
Dynamic: home-page
Dynamic: requires-python
